knext/__init__.py
knext/__pycache__/__init__.cpython-310.pyc
knext/builder/__init__.py
knext/builder/builder_chain_abc.py
knext/builder/client.py
knext/builder/__pycache__/__init__.cpython-310.pyc
knext/builder/__pycache__/builder_chain_abc.cpython-310.pyc
knext/builder/operator/__init__.py
knext/builder/operator/base.py
knext/builder/rest/__init__.py
knext/builder/rest/builder_api.py
knext/builder/rest/models/__init__.py
knext/builder/rest/models/writer_graph_request.py
knext/command/__init__.py
knext/command/exception.py
knext/command/knext_cli.py
knext/command/__pycache__/__init__.cpython-310.pyc
knext/command/__pycache__/exception.cpython-310.pyc
knext/command/__pycache__/knext_cli.cpython-310.pyc
knext/command/sub_command/__init__.py
knext/command/sub_command/builder.py
knext/command/sub_command/project.py
knext/command/sub_command/reasoner.py
knext/command/sub_command/schema.py
knext/command/sub_command/__pycache__/__init__.cpython-310.pyc
knext/command/sub_command/__pycache__/project.cpython-310.pyc
knext/command/sub_command/__pycache__/reasoner.cpython-310.pyc
knext/command/sub_command/__pycache__/schema.cpython-310.pyc
knext/common/__init__.py
knext/common/cache.py
knext/common/env.py
knext/common/utils.py
knext/common/__pycache__/__init__.cpython-310.pyc
knext/common/__pycache__/cache.cpython-310.pyc
knext/common/__pycache__/env.cpython-310.pyc
knext/common/__pycache__/utils.cpython-310.pyc
knext/common/base/__init__.py
knext/common/base/chain.py
knext/common/base/client.py
knext/common/base/component.py
knext/common/base/restable.py
knext/common/base/runnable.py
knext/common/base/__pycache__/__init__.cpython-310.pyc
knext/common/base/__pycache__/chain.cpython-310.pyc
knext/common/base/__pycache__/client.cpython-310.pyc
knext/common/base/__pycache__/component.cpython-310.pyc
knext/common/base/__pycache__/restable.cpython-310.pyc
knext/common/base/__pycache__/runnable.cpython-310.pyc
knext/common/rest/__init__.py
knext/common/rest/api_client.py
openspg_knext-0.5.20241025.1.dist-info/LICENSE
openspg_knext-0.5.20241025.1.dist-info/METADATA
openspg_knext-0.5.20241025.1.dist-info/WHEEL
openspg_knext-0.5.20241025.1.dist-info/entry_points.txt
openspg_knext-0.5.20241025.1.dist-info/top_level.txt
openspg_knext-0.5.20241025.1.dist-info/RECORD
