Metadata-Version: 2.1
Name: openspg-knext
Version: 0.5.20241025.1
Summary: knext
Home-page: https://github.com/OpenSPG/openspg
License: UNKNOWN
Platform: UNKNOWN
Requires-Python: >=3.8
License-File: LICENSE
Requires-Dist: wget ==3.2
Requires-Dist: pytest ==7.4.2
Requires-Dist: json5
Requires-Dist: retrying ==1.3.4
Requires-Dist: tabulate ==0.9.0
Requires-Dist: jieba ==0.42.1
Requires-Dist: nltk ==3.8.1
Requires-Dist: tqdm ==4.66.1
Requires-Dist: six ==1.16.0
Requires-Dist: click ==8.1.7
Requires-Dist: dateutils ==0.6.12
Requires-Dist: certifi ==2023.11.17
Requires-Dist: urllib3 ==2.1.0
Requires-Dist: python-dateutil ==2.8.2
Requires-Dist: networkx ==3.1
Requires-Dist: pydantic ==2.5.2
Requires-Dist: requests ==2.31.0
Requires-Dist: setuptools ==60.2.0
Requires-Dist: psutil
Requires-Dist: Jinja2 ==3.0.3
Requires-Dist: cachetools ==5.3.2
Requires-Dist: numpy ==1.23.1
Requires-Dist: langchain-text-splitters ==0.0.1
Requires-Dist: langchain-community
Requires-Dist: pypdf
Requires-Dist: pandas
Requires-Dist: pycryptodome
Requires-Dist: markdown
Requires-Dist: bs4
Requires-Dist: protobuf ==3.20.1
Requires-Dist: dashscope
Requires-Dist: deprecated
Requires-Dist: schedule
Requires-Dist: openai
Requires-Dist: python-docx
Requires-Dist: charset-normalizer ==3.3.2
Requires-Dist: pdfminer.six ==20231228
